{
  "Aatrox": {
    "id": "Aatrox",
    "key": "266",
    "championName": "Aatrox",
    "title": "the Darkin Blade",
    "mainRole": "Top",
    "tags": [
      "Fighter",
      "Tank"
    ],
    "stats": {
      "hp": 580,
      "hpperlevel": 90,
      "mp": 0,
      "mpperlevel": 0,
      "attackdamage": 60,
      "attackdamageperlevel": 5,
      "attackspeed": 0.651,
      "attackspeedperlevel": 2.5,
      "attackrange": 175,
      "movespeed": 345,
      "hpregen": 3,
      "hpregenperlevel": 1,
      "mpregen": 0,
      "mpregenperlevel": 0,
      "armor": 38,
      "armorperlevel": 3.25,
      "magicresist": 32.1,
      "magicresistperlevel": 1.25
    },
    "abilities": {
      "passive": {
        "name": "Deathbringer Stance"
      },
      "q": {
        "name": "The Darkin Blade"
      },
      "w": {
        "name": "Infernal Chains"
      },
      "e": {
        "name": "Umbral Dash"
      },
      "ult": {
        "name": "World Ender"
      }
    }
  },
  "Ahri": {
    "id": "Ahri",
    "key": "103",
    "championName": "Ahri",
    "title": "the Nine-Tailed Fox",
    "mainRole": "Mid",
    "tags": [
      "Mage",
      "Assassin"
    ],
    "stats": {
      "hp": 526,
      "hpperlevel": 92,
      "mp": 418,
      "mpperlevel": 25,
      "attackdamage": 53.04,
      "attackdamageperlevel": 3,
      "attackspeed": 0.668,
      "attackspeedperlevel": 2,
      "attackrange": 550,
      "movespeed": 330,
      "hpregen": 6.5,
      "hpregenperlevel": 0.6,
      "mpregen": 8,
      "mpregenperlevel": 0.8,
      "armor": 20.88,
      "armorperlevel": 3.5,
      "magicresist": 30,
      "magicresistperlevel": 0.5
    },
    "abilities": {
      "passive": {
        "name": "Vastayan Grace"
      },
      "q": {
        "name": "Orb of Deception"
      },
      "w": {
        "name": "Fox-Fire"
      },
      "e": {
        "name": "Charm"
      },
      "ult": {
        "name": "Spirit Rush"
      }
    }
  },
  "Akali": {
    "id": "Akali",
    "key": "84",
    "championName": "Akali",
    "title": "the Rogue Assassin",
    "mainRole": "Mid",
    "tags": [
      "Assassin"
    ],
    "stats": {
      "hp": 575,
      "hpperlevel": 95,
      "mp": 200,
      "mpperlevel": 0,
      "attackdamage": 62.4,
      "attackdamageperlevel": 3.3,
      "attackspeed": 0.625,
      "attackspeedperlevel": 3.2,
      "attackrange": 125,
      "movespeed": 345,
      "hpregen": 8,
      "hpregenperlevel": 0.5,
      "mpregen": 50,
      "mpregenperlevel": 0,
      "armor": 23,
      "armorperlevel": 3.5,
      "magicresist": 37,
      "magicresistperlevel": 1.25
    },
    "abilities": {
      "passive": {
        "name": "Assassin's Mark"
      },
      "q": {
        "name": "Five Point Strike"
      },
      "w": {
        "name": "Twilight Shroud"
      },
      "e": {
        "name": "Shuriken Flip"
      },
      "ult": {
        "name": "Perfect Execution"
      }
    }
  },
  "Alistar": {
    "id": "Alistar",
    "key": "12",
    "championName": "Alistar",
    "title": "the Minotaur",
    "mainRole": "Support",
    "tags": [
      "Tank"
    ],
    "stats": {
      "hp": 575,
      "hpperlevel": 106,
      "mp": 278.84,
      "mpperlevel": 38,
      "attackdamage": 62,
      "attackdamageperlevel": 3.75,
      "attackspeed": 0.625,
      "attackspeedperlevel": 2.125,
      "attackrange": 125,
      "movespeed": 330,
      "hpregen": 8.5,
      "hpregenperlevel": 0.85,
      "mpregen": 8.5,
      "mpregenperlevel": 0.8,
      "armor": 44,
      "armorperlevel": 3.5,
      "magicresist": 32.1,
      "magicresistperlevel": 1.25
    },
    "abilities": {
      "passive": {
        "name": "Triumphant Roar"
      },
      "q": {
        "name": "Pulverize"
      },
      "w": {
        "name": "Headbutt"
      },
      "e": {
        "name": "Trample"
      },
      "ult": {
        "name": "Unbreakable Will"
      }
    }
  },
  "Amumu": {
    "id": "Amumu",
    "key": "32",
    "championName": "Amumu",
    "title": "the Sad Mummy",
    "mainRole": "Jungle",
    "tags": [
      "Tank",
      "Mage"
    ],
    "stats": {
      "hp": 613.12,
      "hpperlevel": 84,
      "mp": 287.2,
      "mpperlevel": 40,
      "attackdamage": 53.38,
      "attackdamageperlevel": 3.8,
      "attackspeed": 0.736,
      "attackspeedperlevel": 2.18,
      "attackrange": 125,
      "movespeed": 335,
      "hpregen": 9,
      "hpregenperlevel": 0.85,
      "mpregen": 7.382,
      "mpregenperlevel": 0.525,
      "armor": 33,
      "armorperlevel": 3.8,
      "magicresist": 32.1,
      "magicresistperlevel": 1.25
    },
    "abilities": {
      "passive": {
        "name": "Cursed Touch"
      },
      "q": {
        "name": "Bandage Toss"
      },
      "w": {
        "name": "Despair"
      },
      "e": {
        "name": "Tantrum"
      },
      "ult": {
        "name": "Curse of the Sad Mummy"
      }
    }
  },
  "Anivia": {
    "id": "Anivia",
    "key": "34",
    "championName": "Anivia",
    "title": "the Cryophoenix",
    "mainRole": "Mid",
    "tags": [
      "Mage",
      "Crowd Control"
    ],
    "stats": {
      "hp": 480,
      "hpperlevel": 82,
      "mp": 495,
      "mpperlevel": 25,
      "attackdamage": 51.376,
      "attackdamageperlevel": 3.2,
      "attackspeed": 0.625,
      "attackspeedperlevel": 1.68,
      "attackrange": 600,
      "movespeed": 325,
      "hpregen": 5.5,
      "hpregenperlevel": 0.55,
      "mpregen": 8,
      "mpregenperlevel": 0.8,
      "armor": 21.22,
      "armorperlevel": 4,
      "magicresist": 30,
      "magicresistperlevel": 0.5
    },
    "abilities": {
      "passive": {
        "name": "Rebirth"
      },
      "q": {
        "name": "Flash Frost"
      },
      "w": {
        "name": "Crystallize"
      },
      "e": {
        "name": "Frostbite"
      },
      "ult": {
        "name": "Glacial Storm"
      }
    }
  },
  "Annie": {
    "id": "Annie",
    "key": "1",
    "championName": "Annie",
    "title": "the Dark Child",
    "mainRole": "Mid",
    "tags": [
      "Mage",
      "Support",
      "Crowd Control"
    ],
    "stats": {
      "hp": 524,
      "hpperlevel": 88,
      "mp": 418,
      "mpperlevel": 25,
      "attackdamage": 50.41,
      "attackdamageperlevel": 2.625,
      "attackspeed": 0.579,
      "attackspeedperlevel": 1.36,
      "attackrange": 625,
      "movespeed": 335,
      "hpregen": 5.5,
      "hpregenperlevel": 0.55,
      "mpregen": 8,
      "mpregenperlevel": 0.8,
      "armor": 19.22,
      "armorperlevel": 4,
      "magicresist": 30,
      "magicresistperlevel": 0.5
    },
    "abilities": {
      "passive": {
        "name": "Pyromania"
      },
      "q": {
        "name": "Disintegrate"
      },
      "w": {
        "name": "Incinerate"
      },
      "e": {
        "name": "Molten Shield"
      },
      "ult": {
        "name": "Summon: Tibbers"
      }
    }
  },
  "Aphelios": {
    "id": "Aphelios",
    "key": "",
    "championName": "Aphelios",
    "title": "the Weapon of the Faithful",
    "mainRole": "ADC",
    "tags": [
      "Carry",
      "DPS",
      "Utility"
    ],
    "stats": {
      "hp": 530,
      "hpperlevel": 86,
      "mp": ,
      "mpperlevel": ,
      "attackdamage": 57,
      "attackdamageperlevel": 2.2,
      "attackspeed": ,
      "attackspeedperlevel": 2.1,
      "attackrange": ,
      "movespeed": 330,
      "hpregen": 3.25,
      "hpregenperlevel": 0.55,
      "mpregen": ,
      "mpregenperlevel": ,
      "armor": 28,
      "armorperlevel": 3,
      "magicresist": 26,
      "magicresistperlevel": 0.5
    },
    "abilities": {
      "passive": {
        "name": "The Hitman and the Seer"
      },
      "q": {
        "name": "Weapon Abilities"
      },
      "w": {
        "name": "Phase"
      },
      "e": {
        "name": "Weapon Queue System"
      },
      "ult": {
        "name": "Moonlight Vigil"
      }
    }
  },
  "Ashe": {
    "id": "Ashe",
    "key": "22",
    "championName": "Ashe",
    "title": "the Frost Archer",
    "mainRole": "ADC",
    "tags": [
      "Carry",
      "Utility",
      "Poke"
    ],
    "stats": {
      "hp": 539,
      "hpperlevel": 85,
      "mp": 280,
      "mpperlevel": 32,
      "attackdamage": 61,
      "attackdamageperlevel": 2.96,
      "attackspeed": 0.658,
      "attackspeedperlevel": 3.33,
      "attackrange": 600,
      "movespeed": 325,
      "hpregen": 3.5,
      "hpregenperlevel": 0.55,
      "mpregen": 6.972,
      "mpregenperlevel": 0.4,
      "armor": 26,
      "armorperlevel": 3.4,
      "magicresist": 30,
      "magicresistperlevel": 0.5
    },
    "abilities": {
      "passive": {
        "name": "Frost Shot"
      },
      "q": {
        "name": "Ranger's Focus"
      },
      "w": {
        "name": "Volley"
      },
      "e": {
        "name": "Hawkshot"
      },
      "ult": {
        "name": "Enhanced Crystal Arrow"
      }
    }
  }
}